gaussian_suite/__init__.py
gaussian_suite/__version__.py
gaussian_suite/basis_ecp_data.py
gaussian_suite/cd_extractor.py
gaussian_suite/cli.py
gaussian_suite/extractor.py
gaussian_suite/gen_input.py
gaussian_suite/gen_job.py
gaussian_suite/infrared.py
gaussian_suite/opt_extractor.py
gaussian_suite-1.14.2.dist-info/licenses/LICENSE
gaussian_suite-1.14.2.dist-info/METADATA
gaussian_suite-1.14.2.dist-info/WHEEL
gaussian_suite-1.14.2.dist-info/entry_points.txt
gaussian_suite-1.14.2.dist-info/top_level.txt
gaussian_suite-1.14.2.dist-info/RECORD
