Metadata-Version: 2.4
Name: gaussian_suite
Version: 1.14.2
Summary: A package for working with Gaussian input and output files
Home-page: https://gitlab.com/chilton-group/gaussian_suite
Author: Chilton Group
Author-email: nicholas.chilton@manchester.ac.uk
Project-URL: Bug Tracker, https://gitlab.com/chilton-group/gaussian_suite/-/issues
Project-URL: Documentation, https://chilton-group.gitlab.io/gaussian_suite
Classifier: Programming Language :: Python :: 3
Classifier: License :: OSI Approved :: GNU General Public License v3 (GPLv3)
Classifier: Operating System :: OS Independent
Requires-Python: >=3.10
License-File: LICENSE
Requires-Dist: numpy
Requires-Dist: scipy
Requires-Dist: xyz_py>=5.0.0
Requires-Dist: requests
Requires-Dist: hpc_suite>=1.8.0
Requires-Dist: deprecation
Dynamic: author
Dynamic: author-email
Dynamic: classifier
Dynamic: description
Dynamic: description-content-type
Dynamic: home-page
Dynamic: license-file
Dynamic: project-url
Dynamic: requires-dist
Dynamic: requires-python
Dynamic: summary
